odoo/addons/l10n_it_accompanying_invoice/README.rst
odoo/addons/l10n_it_accompanying_invoice/__init__.py
odoo/addons/l10n_it_accompanying_invoice/__manifest__.py
odoo/addons/l10n_it_accompanying_invoice/i18n/it.po
odoo/addons/l10n_it_accompanying_invoice/i18n/l10n_it_accompanying_invoice.pot
odoo/addons/l10n_it_accompanying_invoice/models/__init__.py
odoo/addons/l10n_it_accompanying_invoice/models/account_move.py
odoo/addons/l10n_it_accompanying_invoice/models/sale_order.py
odoo/addons/l10n_it_accompanying_invoice/readme/CONTRIBUTORS.md
odoo/addons/l10n_it_accompanying_invoice/readme/DESCRIPTION.md
odoo/addons/l10n_it_accompanying_invoice/readme/USAGE.md
odoo/addons/l10n_it_accompanying_invoice/static/description/icon.png
odoo/addons/l10n_it_accompanying_invoice/static/description/index.html
odoo/addons/l10n_it_accompanying_invoice/tests/__init__.py
odoo/addons/l10n_it_accompanying_invoice/tests/test_account_move.py
odoo/addons/l10n_it_accompanying_invoice/tests/test_report.py
odoo/addons/l10n_it_accompanying_invoice/tests/test_sale_order.py
odoo/addons/l10n_it_accompanying_invoice/views/account.xml
odoo/addons/l10n_it_accompanying_invoice/views/report_invoice.xml
odoo_addon_l10n_it_accompanying_invoice-18.0.1.0.0.2.dist-info/METADATA
odoo_addon_l10n_it_accompanying_invoice-18.0.1.0.0.2.dist-info/WHEEL
odoo_addon_l10n_it_accompanying_invoice-18.0.1.0.0.2.dist-info/top_level.txt
odoo_addon_l10n_it_accompanying_invoice-18.0.1.0.0.2.dist-info/RECORD
